ACKNOWLEDGEMENTS.md
ARCHITECTURE.md
CHANGELOG.md
CODING_STANDARD.md
CONTRIBUTING.md
EXTENDING.md
FAQ.md
LICENSE
MANIFEST.in
README.md
setup.cfg
setup.py
izi/__init__.py
izi/_async.py
izi/_empty.py
izi/_version.py
izi/api.py
izi/authentication.py
izi/decorators.py
izi/defaults.py
izi/development_runner.py
izi/directives.py
izi/exceptions.py
izi/format.py
izi/input_format.py
izi/interface.py
izi/introspect.py
izi/json_module.py
izi/middleware.py
izi/output_format.py
izi/redirect.py
izi/route.py
izi/routing.py
izi/store.py
izi/test.py
izi/transform.py
izi/types.py
izi/use.py
izi/validate.py
izir.egg-info/PKG-INFO
izir.egg-info/SOURCES.txt
izir.egg-info/dependency_links.txt
izir.egg-info/entry_points.txt
izir.egg-info/requires.txt
izir.egg-info/top_level.txt